move/__init__.py
move/__main__.py
move/analysis/__init__.py
move/analysis/metrics.py
move/conf/__init__.py
move/conf/main.yaml
move/conf/schema.py
move/conf/data/base_data.yaml
move/conf/task/analyze_latent.yaml
move/conf/task/identify_associations_bayes.yaml
move/conf/task/identify_associations_ks.yaml
move/conf/task/identify_associations_ttest.yaml
move/conf/task/tune_model_reconstruction.yaml
move/conf/task/tune_model_stability.yaml
move/core/__init__.py
move/core/logging.py
move/core/seed.py
move/core/typing.py
move/data/__init__.py
move/data/dataloaders.py
move/data/io.py
move/data/perturbations.py
move/data/preprocessing.py
move/models/__init__.py
move/models/vae.py
move/tasks/__init__.py
move/tasks/analyze_latent.py
move/tasks/encode_data.py
move/tasks/identify_associations.py
move/tasks/tune_model.py
move/training/__init__.py
move/training/training_loop.py
move/visualization/__init__.py
move/visualization/dataset_distributions.py
move/visualization/feature_importance.py
move/visualization/latent_space.py
move/visualization/loss_curves.py
move/visualization/metrics.py
move/visualization/style.py
move/visualization/vae_visualization.py
move_dl-1.5.0.dist-info/LICENSE
move_dl-1.5.0.dist-info/METADATA
move_dl-1.5.0.dist-info/WHEEL
move_dl-1.5.0.dist-info/entry_points.txt
move_dl-1.5.0.dist-info/top_level.txt
move_dl-1.5.0.dist-info/RECORD
