Metadata-Version: 2.1
Name: move-dl
Version: 1.5.0
Summary: Multi-omics variational autoencoder
Home-page: https://github.com/RasmussenLab/MOVE
Classifier: Intended Audience :: Healthcare Industry
Classifier: Intended Audience :: Science/Research
Classifier: License :: OSI Approved :: MIT License
Classifier: Programming Language :: Python :: 3
Classifier: Topic :: Scientific/Engineering :: Bio-Informatics
Requires-Python: >=3.9
License-File: LICENSE
Requires-Dist: hydra-core
Requires-Dist: numpy<2
Requires-Dist: pandas
Requires-Dist: torch
Requires-Dist: matplotlib
Requires-Dist: seaborn
Requires-Dist: scikit-learn
Requires-Dist: scipy>=1.10.0
